shtcoding/__init__.py
shtcoding/shtcoding.py
shtcoding-0.1.dist-info/METADATA
shtcoding-0.1.dist-info/WHEEL
shtcoding-0.1.dist-info/top_level.txt
shtcoding-0.1.dist-info/RECORD
