Metadata-Version: 2.1
Name: shtcoding
Version: 0.1
Summary: Python functions for controlling Arduino devices
Home-page: UNKNOWN
Author: p00pin0
Author-email: sht060117@gmail.com
License: UNKNOWN
Platform: UNKNOWN
Requires-Dist: pyserial
